jhwhois/__init__.py
jhwhois/__main__.py
jhwhois/cli.py
jhwhois/util/__init__.py
jhwhois/util/argparse.py
jhwhois/whois/__init__.py
jhwhois/whois/asn_mapping.py
jhwhois/whois/exceptions.py
jhwhois/whois/servers.py
jhwhois/whois/whoisc.py
jhwhois-0.2.8.dist-info/LICENSE.txt
jhwhois-0.2.8.dist-info/METADATA
jhwhois-0.2.8.dist-info/WHEEL
jhwhois-0.2.8.dist-info/entry_points.txt
jhwhois-0.2.8.dist-info/top_level.txt
jhwhois-0.2.8.dist-info/RECORD
