Metadata-Version: 2.1
Name: jhwhois
Version: 0.2.8
Summary: A modern whois client
Author: Johan Hedberg
License: MIT License
Project-URL: repository, https://github.com/crazzy/jhwhois
Keywords: whois
Classifier: Development Status :: 4 - Beta
Classifier: Environment :: Console
Classifier: Intended Audience :: System Administrators
Classifier: License :: OSI Approved :: MIT License
Classifier: Operating System :: POSIX
Classifier: Programming Language :: Python
Classifier: Topic :: Internet
Classifier: Topic :: System :: Networking
Classifier: Topic :: Utilities
Requires-Python: >=3.11.4
License-File: LICENSE.txt
Requires-Dist: pyunycode >=0.1.1
Requires-Dist: validators >=0.28.3
Provides-Extra: dev
Requires-Dist: flake8 ; extra == 'dev'
